aleksis/apps/kolego/__init__.py
aleksis/apps/kolego/apps.py
aleksis/apps/kolego/frontend/components/AbsenceReasonButtons.vue
aleksis/apps/kolego/frontend/components/AbsenceReasonChip.vue
aleksis/apps/kolego/frontend/components/AbsenceReasonGroupSelect.vue
aleksis/apps/kolego/frontend/components/AbsenceReasonTags.vue
aleksis/apps/kolego/frontend/components/AbsenceReasonTagsField.vue
aleksis/apps/kolego/frontend/components/AbsenceReasons.vue
aleksis/apps/kolego/frontend/components/Absences.vue
aleksis/apps/kolego/frontend/components/Empty.vue
aleksis/apps/kolego/frontend/components/absenceReasonTags.graphql
aleksis/apps/kolego/frontend/components/absenceReasons.graphql
aleksis/apps/kolego/frontend/components/absences.graphql
aleksis/apps/kolego/frontend/components/appName.graphql
aleksis/apps/kolego/frontend/components/helper.graphql
aleksis/apps/kolego/frontend/components/widgets/PlannedAbsencesForPersonWidget.vue
aleksis/apps/kolego/frontend/components/widgets/absences.graphql
aleksis/apps/kolego/frontend/index.js
aleksis/apps/kolego/frontend/messages/ar.json
aleksis/apps/kolego/frontend/messages/de.json
aleksis/apps/kolego/frontend/messages/en.json
aleksis/apps/kolego/frontend/messages/fr.json
aleksis/apps/kolego/frontend/messages/la.json
aleksis/apps/kolego/frontend/messages/ru.json
aleksis/apps/kolego/frontend/messages/tr.json
aleksis/apps/kolego/frontend/messages/uk.json
aleksis/apps/kolego/locale/.keepdir
aleksis/apps/kolego/locale/ar/LC_MESSAGES/django.mo
aleksis/apps/kolego/locale/ar/LC_MESSAGES/django.po
aleksis/apps/kolego/locale/de_DE/LC_MESSAGES/django.mo
aleksis/apps/kolego/locale/de_DE/LC_MESSAGES/django.po
aleksis/apps/kolego/locale/fr/LC_MESSAGES/django.mo
aleksis/apps/kolego/locale/fr/LC_MESSAGES/django.po
aleksis/apps/kolego/locale/la/LC_MESSAGES/django.mo
aleksis/apps/kolego/locale/la/LC_MESSAGES/django.po
aleksis/apps/kolego/locale/nb_NO/LC_MESSAGES/django.mo
aleksis/apps/kolego/locale/nb_NO/LC_MESSAGES/django.po
aleksis_app_kolego-1.0.0.dist-info/LICENCE.rst
aleksis_app_kolego-1.0.0.dist-info/METADATA
aleksis_app_kolego-1.0.0.dist-info/WHEEL
aleksis_app_kolego-1.0.0.dist-info/entry_points.txt
aleksis_app_kolego-1.0.0.dist-info/RECORD
