Metadata-Version: 2.3
Name: AlekSIS-App-Kolego
Version: 1.0.0
Summary: AlekSIS (School Information System) — App Kolego (Staff and Absence Management)
License: EUPL-1.2-or-later
Author: Michael Bauer
Author-email: michael-bauer@posteo.de
Maintainer: Jonathan Weth
Maintainer-email: jonathan.weth@teckids.org
Requires-Python: >=3.10,<4.0
Classifier: Environment :: Web Environment
Classifier: Intended Audience :: Education
Classifier: License :: Other/Proprietary License
Classifier: Programming Language :: Python :: 3
Classifier: Programming Language :: Python :: 3.10
Classifier: Programming Language :: Python :: 3.11
Classifier: Programming Language :: Python :: 3.12
Classifier: Programming Language :: Python :: 3.13
Classifier: Topic :: Education
Requires-Dist: aleksis-core (>=4.0.0,<5.0.0)
Project-URL: Documentation, https://aleksis.org/official/AlekSIS/docs/html/
Project-URL: Homepage, https://aleksis.org
Project-URL: Repository, https://edugit.org/AlekSIS/official/AlekSIS-App-Kolego
